{"countries":{"BEN":{"gas":40.5,"oil":20.0},"BFA":{"hydro":30.0,"oil":146.4,"solar":52.9},"CPV":{"oil":87.8,"solar":5.0},"CIV":{"hydro":599.0,"gas":604.0},"GMB":{"oil":70.4},"GHA":{"hydro":1598.0,"solar":20.0,"gas":490.0},"GIN":{"hydro":418.3,"oil":92.1},"GNB":{"oil":18.2},"LBR":{"oil":13.3,"hydro":60.0},"MLI":{"hydro":311.5},"MRT":{"oil":132.8,"gas":120.0,"solar":33.0,"wind":30.0},"NER":{"coal":37.6,"oil":122.6,"solar":7.0},"NGA":{"gas":4350.0,"solar":10.0,"hydro":1900.0},"SEN":{"oil":470.5,"solar":105.7,"hydro":120.0},"SLE":{"oil":76.0,"hydro":50.0},"TGO":{"oil":101.2,"hydro":65.6,"gas":28.3}}}